vedavaapi/__init__.py
vedavaapi/client/__init__.py
vedavaapi/client/accounts.py
vedavaapi/client/async_requests_helper.py
vedavaapi/client/authorization_helper.py
vedavaapi/client/iiif_import_helper.py
vedavaapi/client/objstore.py
vedavaapi_client-1.23.dist-info/METADATA
vedavaapi_client-1.23.dist-info/WHEEL
vedavaapi_client-1.23.dist-info/top_level.txt
vedavaapi_client-1.23.dist-info/RECORD
