Metadata-Version: 2.1
Name: vedavaapi-client
Version: 1.23
Summary: vedavaapi client
Home-page: https://github.com/vedavaapi/vv-client-python
Author: vedavaapi
License: UNKNOWN
Platform: UNKNOWN
Classifier: Programming Language :: Python :: 3
Classifier: Operating System :: OS Independent
Requires-Dist: requests
